ZMPY3D/ZMPY3D_CLI_BatchShapeScore.py
ZMPY3D/ZMPY3D_CLI_BatchSuperA2B.py
ZMPY3D/ZMPY3D_CLI_BatchZM.py
ZMPY3D/ZMPY3D_CLI_ShapeScore.py
ZMPY3D/ZMPY3D_CLI_SuperA2B.py
ZMPY3D/ZMPY3D_CLI_ZM.py
ZMPY3D/__all__.py
ZMPY3D/__init__.py
ZMPY3D/cache_data/BinomialCache.pkl
ZMPY3D/cache_data/LogG_CLMCache_MaxOrder06.pkl
ZMPY3D/cache_data/LogG_CLMCache_MaxOrder20.pkl
ZMPY3D/lib/__init__.py
ZMPY3D/lib/calculate_ab_rotation_02.py
ZMPY3D/lib/calculate_ab_rotation_02_all.py
ZMPY3D/lib/calculate_bbox_moment06.py
ZMPY3D/lib/calculate_bbox_moment_2_zm05.py
ZMPY3D/lib/calculate_box_by_grid_width.py
ZMPY3D/lib/calculate_molecular_radius03.py
ZMPY3D/lib/calculate_zm_by_ab_rotation01.py
ZMPY3D/lib/eigen_root.py
ZMPY3D/lib/fill_voxel_by_weight_density04.py
ZMPY3D/lib/get_3dzd_121_descriptor02.py
ZMPY3D/lib/get_bbox_moment_xyz_sample01.py
ZMPY3D/lib/get_ca_distance_info.py
ZMPY3D/lib/get_descriptor_property.py
ZMPY3D/lib/get_global_parameter02.py
ZMPY3D/lib/get_mean_invariant03.py
ZMPY3D/lib/get_pdb_xyz_ca02.py
ZMPY3D/lib/get_residue_gaussian_density_cache02.py
ZMPY3D/lib/get_residue_radius_map01.py
ZMPY3D/lib/get_residue_weight_map01.py
ZMPY3D/lib/get_total_residue_weight.py
ZMPY3D/lib/get_transform_matrix_from_ab_list02.py
ZMPY3D/lib/read_file_as_string_list.py
ZMPY3D/lib/set_pdb_xyz_rot_m_01.py
ZMPY3D/lib/write_string_list_as_file.py
ZMPY3D-0.0.2.dist-info/LICENSE
ZMPY3D-0.0.2.dist-info/METADATA
ZMPY3D-0.0.2.dist-info/WHEEL
ZMPY3D-0.0.2.dist-info/entry_points.txt
ZMPY3D-0.0.2.dist-info/top_level.txt
ZMPY3D-0.0.2.dist-info/RECORD
